{
  "source": "https://indoinvite.com/s/1462902/undangan/edit?demo=1",
  "scrapedAt": "2026-07-21",
  "note": "Struktur UI editor Indoinvite untuk referensi. Jangan simpan kredensial di repo.",
  "layout": {
    "preview": "iframe/preview undangan di tengah (edit-frame)",
    "bottomSheet": "panel edit slide-up per section via toEdit1(sectionId)",
    "quickMenu": ["Pengaturan", "Komponen Undangan", "Tema", "Musik", "Warna & Font Tema", "Foto Sampul"]
  },
  "sections": [
    "panggilan-mempelai",
    "nama-acara",
    "data-pria",
    "data-wanita",
    "foto-sampul",
    "foto-pria",
    "foto-wanita",
    "doa",
    "salam-agama",
    "ucapan-pembuka",
    "ucapan-penutup",
    "data-acara",
    "hitung-mundur",
    "love-story",
    "story",
    "galery",
    "susunan-acara",
    "titip-hadiah",
    "kehadiran-edit",
    "custom-form",
    "warna",
    "pilih-music",
    "setting",
    "urutan-komponen",
    "embed-map",
    "auto-scroll",
    "watermark-footer"
  ],
  "keyFields": [
    "nama_acara",
    "nama_panggilan_pria",
    "nama_panggilan_wanita",
    "nama_pria",
    "nama_wanita",
    "ig_pria",
    "ig_wanita",
    "doa",
    "countdown_acara",
    "nama_acara1",
    "date_acara",
    "alamat_acara",
    "custom_judul_love_story",
    "c_story"
  ]
}
